musket_ml/__init__.py
musket_ml/examples/.meta/error.log
musket_ml/examples/.meta/meta.yaml
musket_ml/examples/.meta/output.log
musket_ml/examples/data/salt.csv
musket_ml/examples/data/saltExists.csv
musket_ml/examples/data/train.csv
musket_ml/examples/data/images/000e218f21.png
musket_ml/examples/data/images/003c477d7c.png
musket_ml/examples/data/images/008a50a2ec.png
musket_ml/examples/data/images/00950d1627.png
musket_ml/examples/data/images/00a3af90ab.png
musket_ml/examples/experiments/t1/config.yaml
musket_ml/examples/experiments/t2/config.yaml
musket_ml/examples/experiments/t3/config.yaml
musket_ml/examples/modules/datasets.py
musket_ml/examples/modules/__pycache__/datasets.cpython-36.pyc
musket_ml-0.499.dist-info/LICENSE
musket_ml-0.499.dist-info/METADATA
musket_ml-0.499.dist-info/WHEEL
musket_ml-0.499.dist-info/top_level.txt
musket_ml-0.499.dist-info/RECORD
