Metadata-Version: 2.1
Name: musket-ml
Version: 0.499
Summary: Common parts of my pipelines
Home-page: https://github.com/petrochenko-pavel-a/musket_core
Author: Petrochenko Pavel
Author-email: petrochenko.pavel.a@gmail.com
License: MIT
Platform: UNKNOWN
Requires-Dist: musket-text (>=0.443)
Requires-Dist: musket-core (>=0.498)
Requires-Dist: classification-pipeline (>=0.432)
Requires-Dist: segmentation-pipeline (>=0.432)
